pysocketcan/__init__.py
pysocketcan/pysocketcan.py
pysocketcan/scripts.py
pysocketcan-0.0.2.dist-info/LICENSE
pysocketcan-0.0.2.dist-info/METADATA
pysocketcan-0.0.2.dist-info/WHEEL
pysocketcan-0.0.2.dist-info/top_level.txt
pysocketcan-0.0.2.dist-info/RECORD
