Metadata-Version: 2.1
Name: pysocketcan
Version: 0.0.2
Summary: Python wrapper around common Linux SocketCAN commands
Home-page: https://github.com/Tbruno25/pysocketcan
Author: Tj Bruno
Author-email: Tbruno25@gmail.com
License: UNKNOWN
Platform: UNKNOWN
